[
  {
    "name": "Meghan Todd",
    "img": "https://i.ibb.co/F5d1rSy/mechanic-1.jpg",
    "id": 1
  },
  {
    "name": "Zeus Christensen",
    "img": "https://i.ibb.co/MMqZVZs/mechanic-2.jpg",
    "id": 3
  },
  {
    "name": "Dieter Middleton",
    "img": "https://i.ibb.co/wdydS9T/mechanic-3.jpg",
    "id": 2
  },
  {
    "name": "Colette Randolph",
    "img": "https://i.ibb.co/NmT5VCN/mechanic-4.jpg",
    "id": 5
  },
  {
    "name": "Seth Cervantes",
    "img": "https://i.ibb.co/6gLQMXp/mechanic-5.jpg",
    "id": 0
  }
]
